netlink/datadog/core/__init__.py
netlink/datadog/core/load_configuration.py
netlink/datadog/core/metric.py
netlink/datadog/core/metric.pyi
netlink/datadog/core/validate_api_key.py
netlink/datadog/core/worker.py
netlink/datadog/core/worker.pyi
netlink_datadog_core-0.0.4.dist-info/entry_points.txt
netlink_datadog_core-0.0.4.dist-info/WHEEL
netlink_datadog_core-0.0.4.dist-info/METADATA
netlink_datadog_core-0.0.4.dist-info/RECORD
