Metadata-Version: 2.1
Name: netlink-datadog-core
Version: 0.0.4
Summary: Integration for Datadog (Core)
Home-page: https://gitlab.com/netlink_python/netlink-datadog-core
License: MIT
Keywords: monitoring datadog
Author: Bernhard Radermacher
Author-email: bernhard.radermacher@netlink-consulting.com
Requires-Python: >=3.7,<3.11
Classifier: License :: OSI Approved :: MIT License
Classifier: Programming Language :: Python :: 3
Classifier: Programming Language :: Python :: 3.10
Classifier: Programming Language :: Python :: 3.7
Classifier: Programming Language :: Python :: 3.8
Classifier: Programming Language :: Python :: 3.9
Classifier: Topic :: Software Development
Requires-Dist: PyYAML
Requires-Dist: datadog-api-client
Requires-Dist: netlink-logging
Project-URL: Repository, https://gitlab.com/netlink_python/netlink-datadog-core
